fritzingpcb/__init__.py
fritzingpcb/array_2d.py
fritzingpcb/board.py
fritzingpcb/breadboard_svg.py
fritzingpcb/cell.py
fritzingpcb/colour_list.py
fritzingpcb/coords.py
fritzingpcb/element.py
fritzingpcb/fritzingpcb.py
fritzingpcb/fzp_xml.py
fritzingpcb/grid_drawing.py
fritzingpcb/helpers.py
fritzingpcb/layout.py
fritzingpcb/parse_yaml.py
fritzingpcb/pcb_shape_mixin.py
fritzingpcb/pcb_svg.py
fritzingpcb/schematic_svg.py
fritzingpcb-0.0.1.dist-info/LICENSE.txt
fritzingpcb-0.0.1.dist-info/METADATA
fritzingpcb-0.0.1.dist-info/WHEEL
fritzingpcb-0.0.1.dist-info/entry_points.txt
fritzingpcb-0.0.1.dist-info/top_level.txt
fritzingpcb-0.0.1.dist-info/RECORD
