Metadata-Version: 2.1
Name: fritzingpcb
Version: 0.0.1
Author-email: Philip Tregoning <Philip.Tregoning@gmail.com>
Project-URL: Documentation, https://github.com/Philip Tregoning/fritzingpcb#readme
Project-URL: Issues, https://github.com/Philip Tregoning/fritzingpcb/issues
Project-URL: Source, https://github.com/Philip Tregoning/fritzingpcb
Classifier: Development Status :: 4 - Beta
Classifier: Programming Language :: Python
Classifier: Programming Language :: Python :: 3.9
Requires-Python: >=3.9
License-File: LICENSE.txt
Requires-Dist: pyyaml
Requires-Dist: click
Requires-Dist: colour
Requires-Dist: svgwrite
